[{"division_id": "ocd-division/country:us/state:ky/sldu:10", "legislators": [{"leg_id": "KYL000021", "full_name": "Dennis Parrett"}], "name": "10", "chamber": "upper", "abbr": "ky", "boundary_id": "ocd-division/country:us/state:ky/sldu:10", "num_seats": 1, "id": "ky-upper-10"}, {"division_id": "ocd-division/country:us/state:ky/sldu:11", "legislators": [{"leg_id": "KYL000025", "full_name": "John Schickel"}], "name": "11", "chamber": "upper", "abbr": "ky", "boundary_id": "ocd-division/country:us/state:ky/sldu:11", "num_seats": 1, "id": "ky-upper-11"}, {"division_id": "ocd-division/country:us/state:ky/sldu:1", "legislators": [{"leg_id": "KYL000148", "full_name": "Stan Humphries"}], "name": "1", "chamber": "upper", "abbr": "ky", "boundary_id": "ocd-division/country:us/state:ky/sldu:1", "num_seats": 1, "id": "ky-upper-1"}, {"division_id": "ocd-division/country:us/state:ky/sldu:12", "legislators": [{"leg_id": "KYL000016", "full_name": "Alice Forgy Kerr"}], "name": "12", "chamber": "upper", "abbr": "ky", "boundary_id": "ocd-division/country:us/state:ky/sldu:12", "num_seats": 1, "id": "ky-upper-12"}, {"division_id": "ocd-division/country:us/state:ky/sldu:13", "legislators": [{"leg_id": "KYL000204", "full_name": "Reginald Thomas"}], "name": "13", "chamber": "upper", "abbr": "ky", "boundary_id": "ocd-division/country:us/state:ky/sldu:13", "num_seats": 1, "id": "ky-upper-13"}, {"division_id": "ocd-division/country:us/state:ky/sldu:14", "legislators": [{"leg_id": "KYL000012", "full_name": "Jimmy Higdon"}], "name": "14", "chamber": "upper", "abbr": "ky", "boundary_id": "ocd-division/country:us/state:ky/sldu:14", "num_seats": 1, "id": "ky-upper-14"}, {"division_id": "ocd-division/country:us/state:ky/sldu:15", "legislators": [{"leg_id": "KYL000146", "full_name": "Chris Girdler"}], "name": "15", "chamber": "upper", "abbr": "ky", "boundary_id": "ocd-division/country:us/state:ky/sldu:15", "num_seats": 1, "id": "ky-upper-15"}, {"division_id": "ocd-division/country:us/state:ky/sldu:16", "legislators": [{"leg_id": "KYL000206", "full_name": "Max Wise"}], "name": "16", "chamber": "upper", "abbr": "ky", "boundary_id": "ocd-division/country:us/state:ky/sldu:16", "num_seats": 1, "id": "ky-upper-16"}, {"division_id": "ocd-division/country:us/state:ky/sldu:17", "legislators": [{"leg_id": "KYL000032", "full_name": "Damon Thayer"}], "name": "17", "chamber": "upper", "abbr": "ky", "boundary_id": "ocd-division/country:us/state:ky/sldu:17", "num_seats": 1, "id": "ky-upper-17"}, {"division_id": "ocd-division/country:us/state:ky/sldu:18", "legislators": [{"leg_id": "KYL000034", "full_name": "Robin L. Webb"}], "name": "18", "chamber": "upper", "abbr": "ky", "boundary_id": "ocd-division/country:us/state:ky/sldu:18", "num_seats": 1, "id": "ky-upper-18"}, {"division_id": "ocd-division/country:us/state:ky/sldu:19", "legislators": [{"leg_id": "KYL000150", "full_name": "Morgan McGarvey"}], "name": "19", "chamber": "upper", "abbr": "ky", "boundary_id": "ocd-division/country:us/state:ky/sldu:19", "num_seats": 1, "id": "ky-upper-19"}, {"division_id": "ocd-division/country:us/state:ky/sldu:20", "legislators": [{"leg_id": "KYL000013", "full_name": "Paul Hornback"}], "name": "20", "chamber": "upper", "abbr": "ky", "boundary_id": "ocd-division/country:us/state:ky/sldu:20", "num_seats": 1, "id": "ky-upper-20"}, {"division_id": "ocd-division/country:us/state:ky/sldu:21", "legislators": [{"leg_id": "KYL000151", "full_name": "Albert Robinson"}], "name": "21", "chamber": "upper", "abbr": "ky", "boundary_id": "ocd-division/country:us/state:ky/sldu:21", "num_seats": 1, "id": "ky-upper-21"}, {"division_id": "ocd-division/country:us/state:ky/sldu:2", "legislators": [{"leg_id": "KYL000214", "full_name": "Danny Carroll"}], "name": "2", "chamber": "upper", "abbr": "ky", "boundary_id": "ocd-division/country:us/state:ky/sldu:2", "num_seats": 1, "id": "ky-upper-2"}, {"division_id": "ocd-division/country:us/state:ky/sldu:22", "legislators": [{"leg_id": "KYL000003", "full_name": "Tom Buford"}], "name": "22", "chamber": "upper", "abbr": "ky", "boundary_id": "ocd-division/country:us/state:ky/sldu:22", "num_seats": 1, "id": "ky-upper-22"}, {"division_id": "ocd-division/country:us/state:ky/sldu:23", "legislators": [{"leg_id": "KYL000149", "full_name": "Christian McDaniel"}], "name": "23", "chamber": "upper", "abbr": "ky", "boundary_id": "ocd-division/country:us/state:ky/sldu:23", "num_seats": 1, "id": "ky-upper-23"}, {"division_id": "ocd-division/country:us/state:ky/sldu:24", "legislators": [{"leg_id": "KYL000209", "full_name": "Wil Schroder"}], "name": "24", "chamber": "upper", "abbr": "ky", "boundary_id": "ocd-division/country:us/state:ky/sldu:24", "num_seats": 1, "id": "ky-upper-24"}, {"division_id": "ocd-division/country:us/state:ky/sldu:25", "legislators": [{"leg_id": "KYL000031", "full_name": "Robert Stivers"}], "name": "25", "chamber": "upper", "abbr": "ky", "boundary_id": "ocd-division/country:us/state:ky/sldu:25", "num_seats": 1, "id": "ky-upper-25"}, {"division_id": "ocd-division/country:us/state:ky/sldu:26", "legislators": [{"leg_id": "KYL000011", "full_name": "Ernie Harris"}], "name": "26", "chamber": "upper", "abbr": "ky", "boundary_id": "ocd-division/country:us/state:ky/sldu:26", "num_seats": 1, "id": "ky-upper-26"}, {"division_id": "ocd-division/country:us/state:ky/sldu:27", "legislators": [{"leg_id": "KYL000230", "full_name": "Stephen West"}], "name": "27", "chamber": "upper", "abbr": "ky", "boundary_id": "ocd-division/country:us/state:ky/sldu:27", "num_seats": 1, "id": "ky-upper-27"}, {"division_id": "ocd-division/country:us/state:ky/sldu:28", "legislators": [{"leg_id": "KYL000220", "full_name": "Ralph Alvarado"}], "name": "28", "chamber": "upper", "abbr": "ky", "boundary_id": "ocd-division/country:us/state:ky/sldu:28", "num_seats": 1, "id": "ky-upper-28"}, {"division_id": "ocd-division/country:us/state:ky/sldu:29", "legislators": [{"leg_id": "KYL000033", "full_name": "Johnny Ray Turner"}], "name": "29", "chamber": "upper", "abbr": "ky", "boundary_id": "ocd-division/country:us/state:ky/sldu:29", "num_seats": 1, "id": "ky-upper-29"}, {"division_id": "ocd-division/country:us/state:ky/sldu:30", "legislators": [{"leg_id": "KYL000028", "full_name": "Brandon Smith"}], "name": "30", "chamber": "upper", "abbr": "ky", "boundary_id": "ocd-division/country:us/state:ky/sldu:30", "num_seats": 1, "id": "ky-upper-30"}, {"division_id": "ocd-division/country:us/state:ky/sldu:31", "legislators": [{"leg_id": "KYL000015", "full_name": "Ray S. Jones"}], "name": "31", "chamber": "upper", "abbr": "ky", "boundary_id": "ocd-division/country:us/state:ky/sldu:31", "num_seats": 1, "id": "ky-upper-31"}, {"division_id": "ocd-division/country:us/state:ky/sldu:3", "legislators": [{"leg_id": "KYL000152", "full_name": "Whitney Westerfield"}], "name": "3", "chamber": "upper", "abbr": "ky", "boundary_id": "ocd-division/country:us/state:ky/sldu:3", "num_seats": 1, "id": "ky-upper-3"}, {"division_id": "ocd-division/country:us/state:ky/sldu:32", "legislators": [{"leg_id": "KYL000037", "full_name": "Mike Wilson"}], "name": "32", "chamber": "upper", "abbr": "ky", "boundary_id": "ocd-division/country:us/state:ky/sldu:32", "num_seats": 1, "id": "ky-upper-32"}, {"division_id": "ocd-division/country:us/state:ky/sldu:33", "legislators": [{"leg_id": "KYL000019", "full_name": "Gerald A. Neal"}], "name": "33", "chamber": "upper", "abbr": "ky", "boundary_id": "ocd-division/country:us/state:ky/sldu:33", "num_seats": 1, "id": "ky-upper-33"}, {"division_id": "ocd-division/country:us/state:ky/sldu:34", "legislators": [{"leg_id": "KYL000004", "full_name": "Jared Carpenter"}], "name": "34", "chamber": "upper", "abbr": "ky", "boundary_id": "ocd-division/country:us/state:ky/sldu:34", "num_seats": 1, "id": "ky-upper-34"}, {"division_id": "ocd-division/country:us/state:ky/sldu:35", "legislators": [{"leg_id": "KYL000010", "full_name": "Denise Harper Angel"}], "name": "35", "chamber": "upper", "abbr": "ky", "boundary_id": "ocd-division/country:us/state:ky/sldu:35", "num_seats": 1, "id": "ky-upper-35"}, {"division_id": "ocd-division/country:us/state:ky/sldu:36", "legislators": [{"leg_id": "KYL000039", "full_name": "Julie Raque Adams"}], "name": "36", "chamber": "upper", "abbr": "ky", "boundary_id": "ocd-division/country:us/state:ky/sldu:36", "num_seats": 1, "id": "ky-upper-36"}, {"division_id": "ocd-division/country:us/state:ky/sldu:37", "legislators": [{"leg_id": "KYL000006", "full_name": "Perry B. Clark"}], "name": "37", "chamber": "upper", "abbr": "ky", "boundary_id": "ocd-division/country:us/state:ky/sldu:37", "num_seats": 1, "id": "ky-upper-37"}, {"division_id": "ocd-division/country:us/state:ky/sldu:38", "legislators": [{"leg_id": "KYL000026", "full_name": "Dan \"Malano\" Seum"}], "name": "38", "chamber": "upper", "abbr": "ky", "boundary_id": "ocd-division/country:us/state:ky/sldu:38", "num_seats": 1, "id": "ky-upper-38"}, {"division_id": "ocd-division/country:us/state:ky/sldu:4", "legislators": [{"leg_id": "KYL000024", "full_name": "Dorsey Ridley"}], "name": "4", "chamber": "upper", "abbr": "ky", "boundary_id": "ocd-division/country:us/state:ky/sldu:4", "num_seats": 1, "id": "ky-upper-4"}, {"division_id": "ocd-division/country:us/state:ky/sldu:5", "legislators": [{"leg_id": "KYL000008", "full_name": "Carroll Gibson"}], "name": "5", "chamber": "upper", "abbr": "ky", "boundary_id": "ocd-division/country:us/state:ky/sldu:5", "num_seats": 1, "id": "ky-upper-5"}, {"division_id": "ocd-division/country:us/state:ky/sldu:6", "legislators": [{"leg_id": "KYL000065", "full_name": "C. B. Embry"}], "name": "6", "chamber": "upper", "abbr": "ky", "boundary_id": "ocd-division/country:us/state:ky/sldu:6", "num_seats": 1, "id": "ky-upper-6"}, {"division_id": "ocd-division/country:us/state:ky/sldu:7", "legislators": [{"leg_id": "KYL000005", "full_name": "Julian M. Carroll"}], "name": "7", "chamber": "upper", "abbr": "ky", "boundary_id": "ocd-division/country:us/state:ky/sldu:7", "num_seats": 1, "id": "ky-upper-7"}, {"division_id": "ocd-division/country:us/state:ky/sldu:8", "legislators": [{"leg_id": "KYL000002", "full_name": "Joe Bowen"}], "name": "8", "chamber": "upper", "abbr": "ky", "boundary_id": "ocd-division/country:us/state:ky/sldu:8", "num_seats": 1, "id": "ky-upper-8"}, {"division_id": "ocd-division/country:us/state:ky/sldu:9", "legislators": [{"leg_id": "KYL000009", "full_name": "David Givens"}], "name": "9", "chamber": "upper", "abbr": "ky", "boundary_id": "ocd-division/country:us/state:ky/sldu:9", "num_seats": 1, "id": "ky-upper-9"}]