[{"division_id": "ocd-division/country:us/state:co/sldu:10", "legislators": [{"leg_id": "COL000107", "full_name": "Owen Hill"}], "name": "10", "chamber": "upper", "abbr": "co", "boundary_id": "ocd-division/country:us/state:co/sldu:10", "num_seats": 1, "id": "co-upper-10"}, {"division_id": "ocd-division/country:us/state:co/sldu:11", "legislators": [{"leg_id": "COL000192", "full_name": "Merrifield, Michael"}], "name": "11", "chamber": "upper", "abbr": "co", "boundary_id": "ocd-division/country:us/state:co/sldu:11", "num_seats": 1, "id": "co-upper-11"}, {"division_id": "ocd-division/country:us/state:co/sldu:1", "legislators": [{"leg_id": "COL000045", "full_name": "Jerry Sonnenberg"}], "name": "1", "chamber": "upper", "abbr": "co", "boundary_id": "ocd-division/country:us/state:co/sldu:1", "num_seats": 1, "id": "co-upper-1"}, {"division_id": "ocd-division/country:us/state:co/sldu:12", "legislators": [{"leg_id": "COL000021", "full_name": "Bill Cadman"}], "name": "12", "chamber": "upper", "abbr": "co", "boundary_id": "ocd-division/country:us/state:co/sldu:12", "num_seats": 1, "id": "co-upper-12"}, {"division_id": "ocd-division/country:us/state:co/sldu:13", "legislators": [{"leg_id": "COL000185", "full_name": "Cooke, John"}], "name": "13", "chamber": "upper", "abbr": "co", "boundary_id": "ocd-division/country:us/state:co/sldu:13", "num_seats": 1, "id": "co-upper-13"}, {"division_id": "ocd-division/country:us/state:co/sldu:14", "legislators": [{"leg_id": "COL000094", "full_name": "John Kefalas"}], "name": "14", "chamber": "upper", "abbr": "co", "boundary_id": "ocd-division/country:us/state:co/sldu:14", "num_seats": 1, "id": "co-upper-14"}, {"division_id": "ocd-division/country:us/state:co/sldu:15", "legislators": [{"leg_id": "COL000024", "full_name": "Kevin Lundberg"}], "name": "15", "chamber": "upper", "abbr": "co", "boundary_id": "ocd-division/country:us/state:co/sldu:15", "num_seats": 1, "id": "co-upper-15"}, {"division_id": "ocd-division/country:us/state:co/sldu:16", "legislators": [{"leg_id": "COL000194", "full_name": "Neville T., Tim"}], "name": "16", "chamber": "upper", "abbr": "co", "boundary_id": "ocd-division/country:us/state:co/sldu:16", "num_seats": 1, "id": "co-upper-16"}, {"division_id": "ocd-division/country:us/state:co/sldu:17", "legislators": [{"leg_id": "COL000082", "full_name": "Matt Jones"}], "name": "17", "chamber": "upper", "abbr": "co", "boundary_id": "ocd-division/country:us/state:co/sldu:17", "num_seats": 1, "id": "co-upper-17"}, {"division_id": "ocd-division/country:us/state:co/sldu:18", "legislators": [{"leg_id": "COL000029", "full_name": "Rollie Heath"}], "name": "18", "chamber": "upper", "abbr": "co", "boundary_id": "ocd-division/country:us/state:co/sldu:18", "num_seats": 1, "id": "co-upper-18"}, {"division_id": "ocd-division/country:us/state:co/sldu:19", "legislators": [{"leg_id": "COL000190", "full_name": "Woods, Laura J."}], "name": "19", "chamber": "upper", "abbr": "co", "boundary_id": "ocd-division/country:us/state:co/sldu:19", "num_seats": 1, "id": "co-upper-19"}, {"division_id": "ocd-division/country:us/state:co/sldu:20", "legislators": [{"leg_id": "COL000005", "full_name": "Cheri Jahn"}], "name": "20", "chamber": "upper", "abbr": "co", "boundary_id": "ocd-division/country:us/state:co/sldu:20", "num_seats": 1, "id": "co-upper-20"}, {"division_id": "ocd-division/country:us/state:co/sldu:21", "legislators": [{"leg_id": "COL000102", "full_name": "Jessie Ulibarri"}], "name": "21", "chamber": "upper", "abbr": "co", "boundary_id": "ocd-division/country:us/state:co/sldu:21", "num_seats": 1, "id": "co-upper-21"}, {"division_id": "ocd-division/country:us/state:co/sldu:2", "legislators": [{"leg_id": "COL000013", "full_name": "Kevin Grantham"}], "name": "2", "chamber": "upper", "abbr": "co", "boundary_id": "ocd-division/country:us/state:co/sldu:2", "num_seats": 1, "id": "co-upper-2"}, {"division_id": "ocd-division/country:us/state:co/sldu:22", "legislators": [{"leg_id": "COL000148", "full_name": "Andy Kerr"}], "name": "22", "chamber": "upper", "abbr": "co", "boundary_id": "ocd-division/country:us/state:co/sldu:22", "num_seats": 1, "id": "co-upper-22"}, {"division_id": "ocd-division/country:us/state:co/sldu:23", "legislators": [{"leg_id": "COL000104", "full_name": "Vicki Marble"}], "name": "23", "chamber": "upper", "abbr": "co", "boundary_id": "ocd-division/country:us/state:co/sldu:23", "num_seats": 1, "id": "co-upper-23"}, {"division_id": "ocd-division/country:us/state:co/sldu:24", "legislators": [{"leg_id": "COL000174", "full_name": "Martinez Humenik, Beth"}], "name": "24", "chamber": "upper", "abbr": "co", "boundary_id": "ocd-division/country:us/state:co/sldu:24", "num_seats": 1, "id": "co-upper-24"}, {"division_id": "ocd-division/country:us/state:co/sldu:25", "legislators": [{"leg_id": "COL000002", "full_name": "Mary Hodge"}], "name": "25", "chamber": "upper", "abbr": "co", "boundary_id": "ocd-division/country:us/state:co/sldu:25", "num_seats": 1, "id": "co-upper-25"}, {"division_id": "ocd-division/country:us/state:co/sldu:26", "legislators": [{"leg_id": "COL000003", "full_name": "Linda Newell"}], "name": "26", "chamber": "upper", "abbr": "co", "boundary_id": "ocd-division/country:us/state:co/sldu:26", "num_seats": 1, "id": "co-upper-26"}, {"division_id": "ocd-division/country:us/state:co/sldu:27", "legislators": [], "name": "27", "chamber": "upper", "abbr": "co", "boundary_id": "ocd-division/country:us/state:co/sldu:27", "num_seats": 1, "id": "co-upper-27"}, {"division_id": "ocd-division/country:us/state:co/sldu:28", "legislators": [{"leg_id": "COL000062", "full_name": "Nancy Todd"}], "name": "28", "chamber": "upper", "abbr": "co", "boundary_id": "ocd-division/country:us/state:co/sldu:28", "num_seats": 1, "id": "co-upper-28"}, {"division_id": "ocd-division/country:us/state:co/sldu:29", "legislators": [{"leg_id": "COL000010", "full_name": "Morgan Carroll"}], "name": "29", "chamber": "upper", "abbr": "co", "boundary_id": "ocd-division/country:us/state:co/sldu:29", "num_seats": 1, "id": "co-upper-29"}, {"division_id": "ocd-division/country:us/state:co/sldu:30", "legislators": [{"leg_id": "COL000057", "full_name": "Chris Holbert"}], "name": "30", "chamber": "upper", "abbr": "co", "boundary_id": "ocd-division/country:us/state:co/sldu:30", "num_seats": 1, "id": "co-upper-30"}, {"division_id": "ocd-division/country:us/state:co/sldu:31", "legislators": [{"leg_id": "COL000030", "full_name": "Pat Steadman"}], "name": "31", "chamber": "upper", "abbr": "co", "boundary_id": "ocd-division/country:us/state:co/sldu:31", "num_seats": 1, "id": "co-upper-31"}, {"division_id": "ocd-division/country:us/state:co/sldu:3", "legislators": [{"leg_id": "COL000182", "full_name": "Garcia, Leroy M."}], "name": "3", "chamber": "upper", "abbr": "co", "boundary_id": "ocd-division/country:us/state:co/sldu:3", "num_seats": 1, "id": "co-upper-3"}, {"division_id": "ocd-division/country:us/state:co/sldu:32", "legislators": [{"leg_id": "COL000035", "full_name": "Irene Aguilar"}], "name": "32", "chamber": "upper", "abbr": "co", "boundary_id": "ocd-division/country:us/state:co/sldu:32", "num_seats": 1, "id": "co-upper-32"}, {"division_id": "ocd-division/country:us/state:co/sldu:33", "legislators": [{"leg_id": "COL000034", "full_name": "Michael Johnston"}], "name": "33", "chamber": "upper", "abbr": "co", "boundary_id": "ocd-division/country:us/state:co/sldu:33", "num_seats": 1, "id": "co-upper-33"}, {"division_id": "ocd-division/country:us/state:co/sldu:34", "legislators": [{"leg_id": "COL000033", "full_name": "Lucia Guzman"}], "name": "34", "chamber": "upper", "abbr": "co", "boundary_id": "ocd-division/country:us/state:co/sldu:34", "num_seats": 1, "id": "co-upper-34"}, {"division_id": "ocd-division/country:us/state:co/sldu:35", "legislators": [{"leg_id": "COL000111", "full_name": "Larry Crowder"}], "name": "35", "chamber": "upper", "abbr": "co", "boundary_id": "ocd-division/country:us/state:co/sldu:35", "num_seats": 1, "id": "co-upper-35"}, {"division_id": "ocd-division/country:us/state:co/sldu:4", "legislators": [{"leg_id": "COL000015", "full_name": "Mark Scheffel"}], "name": "4", "chamber": "upper", "abbr": "co", "boundary_id": "ocd-division/country:us/state:co/sldu:4", "num_seats": 1, "id": "co-upper-4"}, {"division_id": "ocd-division/country:us/state:co/sldu:5", "legislators": [{"leg_id": "COL000186", "full_name": "Donovan, Kerry"}], "name": "5", "chamber": "upper", "abbr": "co", "boundary_id": "ocd-division/country:us/state:co/sldu:5", "num_seats": 1, "id": "co-upper-5"}, {"division_id": "ocd-division/country:us/state:co/sldu:6", "legislators": [{"leg_id": "COL000017", "full_name": "Ellen S. Roberts"}], "name": "6", "chamber": "upper", "abbr": "co", "boundary_id": "ocd-division/country:us/state:co/sldu:6", "num_seats": 1, "id": "co-upper-6"}, {"division_id": "ocd-division/country:us/state:co/sldu:7", "legislators": [{"leg_id": "COL000037", "full_name": "Ray Scott"}], "name": "7", "chamber": "upper", "abbr": "co", "boundary_id": "ocd-division/country:us/state:co/sldu:7", "num_seats": 1, "id": "co-upper-7"}, {"division_id": "ocd-division/country:us/state:co/sldu:8", "legislators": [{"leg_id": "COL000099", "full_name": "Randy Baumgardner"}], "name": "8", "chamber": "upper", "abbr": "co", "boundary_id": "ocd-division/country:us/state:co/sldu:8", "num_seats": 1, "id": "co-upper-8"}, {"division_id": "ocd-division/country:us/state:co/sldu:9", "legislators": [{"leg_id": "COL000018", "full_name": "Kent D. Lambert"}], "name": "9", "chamber": "upper", "abbr": "co", "boundary_id": "ocd-division/country:us/state:co/sldu:9", "num_seats": 1, "id": "co-upper-9"}]